{
  "schema_version": "banned_pattern_v1",
  "id": "pr2632-comment-3374481524",
  "source_pr": 2632,
  "comment_url": "https://github.com/doldecomp/melee/pull/2632#discussion_r3374481524",
  "file": "src/sysdolphin/baselib/particle.c",
  "line": 1085,
  "excerpt": "case 1: msg = \"MCC is no initialize\"; msg = lbl_8040A540;",
  "standard_id": null,
  "detector": {
    "type": "agent_exhibit"
  },
  "comment": "Regression due to not using the string.",
  "disposition": "proposed",
  "reviewer": "PsiLupan",
  "heuristic_matches": [
    "regression"
  ],
  "pr_author": "fjooord",
  "pr_head_repo": "fjooord/melee",
  "pr_state": "MERGED",
  "extracted_at": "2026-06-11T22:53:13Z"
}
